stepwise_mol_bio/__init__.py
stepwise_mol_bio/_assembly.py
stepwise_mol_bio/_utils.py
stepwise_mol_bio/aliquot.py
stepwise_mol_bio/anneal.py
stepwise_mol_bio/conf.toml
stepwise_mol_bio/digest.py
stepwise_mol_bio/direct_dilution.py
stepwise_mol_bio/ethanol_precipitation.py
stepwise_mol_bio/gibson.py
stepwise_mol_bio/golden_gate.py
stepwise_mol_bio/invpcr.py
stepwise_mol_bio/ivt.py
stepwise_mol_bio/ivtt.py
stepwise_mol_bio/kld.py
stepwise_mol_bio/ligate.py
stepwise_mol_bio/lyophilize.py
stepwise_mol_bio/miniprep.py
stepwise_mol_bio/page_purify.py
stepwise_mol_bio/pcr.py
stepwise_mol_bio/phenol_chloroform_extraction.txt
stepwise_mol_bio/qpcr.py
stepwise_mol_bio/retransform.txt
stepwise_mol_bio/rnasezap.txt
stepwise_mol_bio/serial_dilution.py
stepwise_mol_bio/spin_cleanup.py
stepwise_mol_bio/transform.txt
stepwise_mol_bio/gels/__init__.py
stepwise_mol_bio/gels/gel.py
stepwise_mol_bio/gels/laser_scanner.py
stepwise_mol_bio/gels/stain.py
stepwise_mol_bio/gels/uv_transilluminator.py
stepwise_mol_bio/layouts/24_well_plate.pdf
stepwise_mol_bio/layouts/384_well_plate.pdf
stepwise_mol_bio/layouts/96_well_plate.pdf
stepwise_mol_bio-1.23.1.dist-info/entry_points.txt
stepwise_mol_bio-1.23.1.dist-info/LICENSE.txt
stepwise_mol_bio-1.23.1.dist-info/WHEEL
stepwise_mol_bio-1.23.1.dist-info/METADATA
stepwise_mol_bio-1.23.1.dist-info/RECORD
