Metadata-Version: 2.1
Name: stepwise_mol_bio
Version: 1.23.1
Summary: Protocols relating to molecular biology, e.g. PCR.
Home-page: https://github.com/kalekundert/stepwise_mol_bio
Author: Kale Kundert
Author-email: kale@thekunderts.net
Requires-Python: ~=3.8
Classifier: Programming Language :: Python :: 3
Classifier: License :: OSI Approved :: MIT License
Requires-Dist: appcli
Requires-Dist: appdirs
Requires-Dist: autoprop
Requires-Dist: biopython
Requires-Dist: freezerbox
Requires-Dist: inform~=1.21
Requires-Dist: more_itertools~=8.6
Requires-Dist: numpy
Requires-Dist: requests
Requires-Dist: rtoml
Requires-Dist: stepwise
Requires-Dist: tidyexc
Requires-Dist: sphinx ; extra == "doc"
Requires-Dist: sphinx_rtd_theme ; extra == "doc"
Requires-Dist: autoclasstoc ; extra == "doc"
Requires-Dist: pytest ; extra == "test"
Requires-Dist: pytest-cov ; extra == "test"
Requires-Dist: parametrize_from_file ; extra == "test"
Requires-Dist: requests_testing ; extra == "test"
Requires-Dist: re_assert ; extra == "test"
Requires-Dist: coveralls ; extra == "test"
Project-URL: Bug Tracker, https://github.com/kalekundert/stepwise_mol_bio/issues
Project-URL: Continuous Integration, https://github.com/kalekundert/stepwise_mol_bio/actions
Project-URL: Documentation, https://stepwise_mol_bio.readthedocs.io/en/latest/
Project-URL: Test Coverage, https://coveralls.io/github/kalekundert/stepwise_mol_bio
Project-URL: Version Control, https://github.com/kalekundert/stepwise_mol_bio
Provides-Extra: doc
Provides-Extra: test
